kojistatus/__init__.py
kojistatus/__main__.py
kojistatus/status.py
kojistatus/webapp.py
kojistatus-0.3.dist-info/DESCRIPTION.rst
kojistatus-0.3.dist-info/METADATA
kojistatus-0.3.dist-info/RECORD
kojistatus-0.3.dist-info/WHEEL
kojistatus-0.3.dist-info/metadata.json
kojistatus-0.3.dist-info/top_level.txt
